openplaces/__init__.py
openplaces/main.py
openplaces-0.1.0.dist-info/licenses/LICENSE.md
openplaces-0.1.0.dist-info/METADATA
openplaces-0.1.0.dist-info/WHEEL
openplaces-0.1.0.dist-info/top_level.txt
openplaces-0.1.0.dist-info/RECORD
